[
  {
    "source_page":22,
    "text":"KENYA NATIONAL BUREAU OF STATISTICS",
    "value_raw":"",
    "imputed":false
  },
  {
    "source_page":22,
    "text":"Quality Statistics for better lives.",
    "value_raw":"",
    "imputed":false
  },
  {
    "source_page":22,
    "text":"Provide, Manage and Promote quality statistics through utilization of best practices for public use.",
    "value_raw":"",
    "imputed":false
  },
  {
    "source_page":22,
    "text":"CORE VALUES",
    "value_raw":"",
    "imputed":false
  },
  {
    "source_page":22,
    "text":"Professionalism",
    "value_raw":"",
    "imputed":false
  }
]