{
  "Mombasa": {
    "county_name": "Mombasa",
    "county_code": 1,
    "status": "DATA_UNAVAILABLE",
    "file_path": "",
    "size": 0,
    "year": null,
    "all_files": [],
    "file_count": 0,
    "timestamp": "2026-06-07T12:47:13.710980"
  },
  "Kwale": {
    "county_name": "Kwale",
    "county_code": 2,
    "status": "DATA_UNAVAILABLE",
    "file_path": "",
    "size": 0,
    "year": null,
    "all_files": [],
    "file_count": 0,
    "timestamp": "2026-06-07T12:47:13.711359"
  },
  "Kilifi": {
    "county_name": "Kilifi",
    "county_code": 3,
    "status": "DATA_UNAVAILABLE",
    "file_path": "",
    "size": 0,
    "year": null,
    "all_files": [],
    "file_count": 0,
    "timestamp": "2026-06-07T12:47:13.711689"
  },
  "Tana River": {
    "county_name": "Tana River",
    "county_code": 4,
    "status": "DATA_UNAVAILABLE",
    "file_path": "",
    "size": 0,
    "year": null,
    "all_files": [],
    "file_count": 0,
    "timestamp": "2026-06-07T12:47:13.712437"
  },
  "Lamu": {
    "county_name": "Lamu",
    "county_code": 5,
    "status": "DATA_UNAVAILABLE",
    "file_path": "",
    "size": 0,
    "year": null,
    "all_files": [],
    "file_count": 0,
    "timestamp": "2026-06-07T12:47:13.713095"
  },
  "Taita-Taveta": {
    "county_name": "Taita-Taveta",
    "county_code": 6,
    "status": "DATA_UNAVAILABLE",
    "file_path": "",
    "size": 0,
    "year": null,
    "all_files": [],
    "file_count": 0,
    "timestamp": "2026-06-07T12:47:13.713400"
  },
  "Garissa": {
    "county_name": "Garissa",
    "county_code": 7,
    "status": "AVAILABLE",
    "file_path": "D:/personal projects/Project data/Garissa/2024-Statistical-Abstract-Garissa-County.pdf",
    "size": 6604027,
    "year": 2024,
    "all_files": [
      "D:/personal projects/Project data/Garissa/2024-Statistical-Abstract-Garissa-County.pdf"
    ],
    "file_count": 1,
    "timestamp": "2026-06-07T03:01:03.168187"
  },
  "Wajir": {
    "county_name": "Wajir",
    "county_code": 8,
    "status": "DATA_UNAVAILABLE",
    "file_path": "",
    "size": 0,
    "year": null,
    "all_files": [],
    "file_count": 0,
    "timestamp": "2026-06-07T12:47:13.715886"
  },
  "Mandera": {
    "county_name": "Mandera",
    "county_code": 9,
    "status": "DATA_UNAVAILABLE",
    "file_path": "",
    "size": 0,
    "year": null,
    "all_files": [],
    "file_count": 0,
    "timestamp": "2026-06-07T12:47:13.716340"
  },
  "Marsabit": {
    "county_name": "Marsabit",
    "county_code": 10,
    "status": "DATA_UNAVAILABLE",
    "file_path": "",
    "size": 0,
    "year": null,
    "all_files": [],
    "file_count": 0,
    "timestamp": "2026-06-07T12:47:13.716632"
  },
  "Isiolo": {
    "county_name": "Isiolo",
    "county_code": 11,
    "status": "DATA_UNAVAILABLE",
    "file_path": "",
    "size": 0,
    "year": null,
    "all_files": [],
    "file_count": 0,
    "timestamp": "2026-06-07T12:47:13.717027"
  },
  "Meru": {
    "county_name": "Meru",
    "county_code": 12,
    "status": "DATA_UNAVAILABLE",
    "file_path": "",
    "size": 0,
    "year": null,
    "all_files": [],
    "file_count": 0,
    "timestamp": "2026-06-07T12:47:13.717385"
  },
  "Tharaka-Nithi": {
    "county_name": "Tharaka-Nithi",
    "county_code": 13,
    "status": "DATA_UNAVAILABLE",
    "file_path": "",
    "size": 0,
    "year": null,
    "all_files": [],
    "file_count": 0,
    "timestamp": "2026-06-07T12:47:13.717661"
  },
  "Embu": {
    "county_name": "Embu",
    "county_code": 14,
    "status": "DATA_UNAVAILABLE",
    "file_path": "",
    "size": 0,
    "year": null,
    "all_files": [],
    "file_count": 0,
    "timestamp": "2026-06-07T12:47:13.717893"
  },
  "Kitui": {
    "county_name": "Kitui",
    "county_code": 15,
    "status": "DATA_UNAVAILABLE",
    "file_path": "",
    "size": 0,
    "year": null,
    "all_files": [],
    "file_count": 0,
    "timestamp": "2026-06-07T12:47:13.718115"
  },
  "Machakos": {
    "county_name": "Machakos",
    "county_code": 16,
    "status": "DATA_UNAVAILABLE",
    "file_path": "",
    "size": 0,
    "year": null,
    "all_files": [],
    "file_count": 0,
    "timestamp": "2026-06-07T12:47:13.718336"
  },
  "Makueni": {
    "county_name": "Makueni",
    "county_code": 17,
    "status": "AVAILABLE",
    "file_path": "D:/personal projects/Project data/Makueni/2025-Statistical-Abstract-Makueni-County.pdf",
    "size": 6528440,
    "year": 2025,
    "all_files": [
      "D:/personal projects/Project data/Makueni/2020-County-Statistical-Abstracts-Makueni.pdf",
      "D:/personal projects/Project data/Makueni/2021-County-Statistical-Abstracts-Makueni.pdf",
      "D:/personal projects/Project data/Makueni/2022-County-Statistical-Abstracts-Makueni.pdf",
      "D:/personal projects/Project data/Makueni/2023-County-Statistical-Abstract-Makueni-County.pdf",
      "D:/personal projects/Project data/Makueni/2024-Statistical-Abstract-Makueni-County.pdf",
      "D:/personal projects/Project data/Makueni/2025-Statistical-Abstract-Makueni-County.pdf"
    ],
    "file_count": 6,
    "timestamp": "2026-06-07T04:13:18.880492"
  },
  "Nyandarua": {
    "county_name": "Nyandarua",
    "county_code": 18,
    "status": "AVAILABLE",
    "file_path": "D:/personal projects/Project data/Nyandarua/2022-County-Statistical-Abstracts-Nyandarua.pdf",
    "size": 1823772,
    "year": 2022,
    "all_files": [
      "D:/personal projects/Project data/Nyandarua/2022-County-Statistical-Abstracts-Nyandarua.pdf"
    ],
    "file_count": 1,
    "timestamp": "2026-06-07T03:01:13.084964"
  },
  "Nyeri": {
    "county_name": "Nyeri",
    "county_code": 19,
    "status": "DATA_UNAVAILABLE",
    "file_path": "",
    "size": 0,
    "year": null,
    "all_files": [],
    "file_count": 0,
    "timestamp": "2026-06-07T12:47:13.719452"
  },
  "Kirinyaga": {
    "county_name": "Kirinyaga",
    "county_code": 20,
    "status": "AVAILABLE",
    "file_path": "D:/personal projects/Project data/Kirinyaga/2015-County-Statistical-Abstracts-Kirinyaga.pdf",
    "size": 753013,
    "year": 2015,
    "all_files": [
      "D:/personal projects/Project data/Kirinyaga/2015-County-Statistical-Abstracts-Kirinyaga.pdf"
    ],
    "file_count": 1,
    "timestamp": "2026-06-07T03:01:17.113780"
  },
  "Murang'a": {
    "county_name": "Murang'a",
    "county_code": 21,
    "status": "DATA_UNAVAILABLE",
    "file_path": "",
    "size": 0,
    "year": null,
    "all_files": [],
    "file_count": 0,
    "timestamp": "2026-06-07T12:47:13.720457"
  },
  "Kiambu": {
    "county_name": "Kiambu",
    "county_code": 22,
    "status": "DATA_UNAVAILABLE",
    "file_path": "",
    "size": 0,
    "year": null,
    "all_files": [],
    "file_count": 0,
    "timestamp": "2026-06-07T12:47:13.720694"
  },
  "Turkana": {
    "county_name": "Turkana",
    "county_code": 23,
    "status": "DATA_UNAVAILABLE",
    "file_path": "",
    "size": 0,
    "year": null,
    "all_files": [],
    "file_count": 0,
    "timestamp": "2026-06-07T12:47:13.720909"
  },
  "West Pokot": {
    "county_name": "West Pokot",
    "county_code": 24,
    "status": "AVAILABLE",
    "file_path": "D:/personal projects/Project data/West Pokot/2015-County-Statistical-Abstracts-West-Pokot.pdf",
    "size": 624611,
    "year": 2015,
    "all_files": [
      "D:/personal projects/Project data/West Pokot/2015-County-Statistical-Abstracts-West-Pokot.pdf"
    ],
    "file_count": 1,
    "timestamp": "2026-06-07T03:01:21.012180"
  },
  "Samburu": {
    "county_name": "Samburu",
    "county_code": 25,
    "status": "AVAILABLE",
    "file_path": "D:/personal projects/Project data/Samburu/2024-Statistical-Abstract-Samburu-County.pdf",
    "size": 1556611,
    "year": 2024,
    "all_files": [
      "D:/personal projects/Project data/Samburu/2024-Statistical-Abstract-Samburu-County.pdf"
    ],
    "file_count": 1,
    "timestamp": "2026-06-07T03:01:25.494371"
  },
  "Trans Nzoia": {
    "county_name": "Trans Nzoia",
    "county_code": 26,
    "status": "DATA_UNAVAILABLE",
    "file_path": "",
    "size": 0,
    "year": null,
    "all_files": [],
    "file_count": 0,
    "timestamp": "2026-06-07T12:47:13.722515"
  },
  "Uasin Gishu": {
    "county_name": "Uasin Gishu",
    "county_code": 27,
    "status": "AVAILABLE",
    "file_path": "D:/personal projects/Project data/Uasin Gishu/2025-Statistical-Abstract-Uasin-Gishu-County.pdf",
    "size": 20961889,
    "year": 2025,
    "all_files": [
      "D:/personal projects/Project data/Uasin Gishu/2015-County-Statistical-Abstracts-Uasin-Gishu.pdf",
      "D:/personal projects/Project data/Uasin Gishu/2021-County-Statistical-Abstracts-Uasin-Gishu.pdf",
      "D:/personal projects/Project data/Uasin Gishu/2025-Statistical-Abstract-Uasin-Gishu-County.pdf"
    ],
    "file_count": 3,
    "timestamp": "2026-06-07T03:01:38.606906"
  },
  "Elgeyo-Marakwet": {
    "county_name": "Elgeyo-Marakwet",
    "county_code": 28,
    "status": "DATA_UNAVAILABLE",
    "file_path": "",
    "size": 0,
    "year": null,
    "all_files": [],
    "file_count": 0,
    "timestamp": "2026-06-07T12:47:13.723154"
  },
  "Nandi": {
    "county_name": "Nandi",
    "county_code": 29,
    "status": "AVAILABLE",
    "file_path": "D:/personal projects/Project data/Nandi/2015-County-Statistical-Abstracts-Nandi.pdf",
    "size": 711011,
    "year": 2015,
    "all_files": [
      "D:/personal projects/Project data/Nandi/2015-County-Statistical-Abstracts-Nandi.pdf"
    ],
    "file_count": 1,
    "timestamp": "2026-06-07T03:01:42.778082"
  },
  "Baringo": {
    "county_name": "Baringo",
    "county_code": 30,
    "status": "AVAILABLE",
    "file_path": "D:/personal projects/Project data/Baringo/2015-County-Statistical-Abstracts-Baringo.pdf",
    "size": 844547,
    "year": 2015,
    "all_files": [
      "D:/personal projects/Project data/Baringo/2015-County-Statistical-Abstracts-Baringo.pdf"
    ],
    "file_count": 1,
    "timestamp": "2026-06-07T03:01:47.433867"
  },
  "Laikipia": {
    "county_name": "Laikipia",
    "county_code": 31,
    "status": "AVAILABLE",
    "file_path": "D:/personal projects/Project data/Laikipia/2024-Statistical-Abstract-Laikipia-County.pdf",
    "size": 3701099,
    "year": 2024,
    "all_files": [
      "D:/personal projects/Project data/Laikipia/2020-County-Statistical-Abstracts-Laikipia.pdf",
      "D:/personal projects/Project data/Laikipia/2024-Statistical-Abstract-Laikipia-County.pdf"
    ],
    "file_count": 2,
    "timestamp": "2026-06-07T03:01:52.255328"
  },
  "Nakuru": {
    "county_name": "Nakuru",
    "county_code": 32,
    "status": "AVAILABLE",
    "file_path": "D:/personal projects/Project data/Nakuru/2015-County-Statistical-Abstracts-Nakuru.pdf",
    "size": 819068,
    "year": 2015,
    "all_files": [
      "D:/personal projects/Project data/Nakuru/2015-County-Statistical-Abstracts-Nakuru.pdf"
    ],
    "file_count": 1,
    "timestamp": "2026-06-07T03:01:56.175473"
  },
  "Narok": {
    "county_name": "Narok",
    "county_code": 33,
    "status": "AVAILABLE",
    "file_path": "D:/personal projects/Project data/Narok/2015-County-Statistical-Abstracts-Narok.pdf",
    "size": 719459,
    "year": 2015,
    "all_files": [
      "D:/personal projects/Project data/Narok/2015-County-Statistical-Abstracts-Narok.pdf"
    ],
    "file_count": 1,
    "timestamp": "2026-06-07T03:02:00.082857"
  },
  "Kajiado": {
    "county_name": "Kajiado",
    "county_code": 34,
    "status": "DATA_UNAVAILABLE",
    "file_path": "",
    "size": 0,
    "year": null,
    "all_files": [],
    "file_count": 0,
    "timestamp": "2026-06-07T12:47:13.725430"
  },
  "Kericho": {
    "county_name": "Kericho",
    "county_code": 35,
    "status": "DATA_UNAVAILABLE",
    "file_path": "",
    "size": 0,
    "year": null,
    "all_files": [],
    "file_count": 0,
    "timestamp": "2026-06-07T12:47:13.725701"
  },
  "Bomet": {
    "county_name": "Bomet",
    "county_code": 36,
    "status": "DATA_UNAVAILABLE",
    "file_path": "",
    "size": 0,
    "year": null,
    "all_files": [],
    "file_count": 0,
    "timestamp": "2026-06-07T12:47:13.726251"
  },
  "Kakamega": {
    "county_name": "Kakamega",
    "county_code": 37,
    "status": "DATA_UNAVAILABLE",
    "file_path": "",
    "size": 0,
    "year": null,
    "all_files": [],
    "file_count": 0,
    "timestamp": "2026-06-07T12:47:13.727178"
  },
  "Vihiga": {
    "county_name": "Vihiga",
    "county_code": 38,
    "status": "DATA_UNAVAILABLE",
    "file_path": "",
    "size": 0,
    "year": null,
    "all_files": [],
    "file_count": 0,
    "timestamp": "2026-06-07T12:47:13.727697"
  },
  "Bungoma": {
    "county_name": "Bungoma",
    "county_code": 39,
    "status": "AVAILABLE",
    "file_path": "D:/personal projects/Project data/Bungoma/2015-County-Statistical-Abstracts-Bungoma.pdf",
    "size": 695477,
    "year": 2015,
    "all_files": [
      "D:/personal projects/Project data/Bungoma/2015-County-Statistical-Abstracts-Bungoma.pdf"
    ],
    "file_count": 1,
    "timestamp": "2026-06-07T03:02:04.018534"
  },
  "Busia": {
    "county_name": "Busia",
    "county_code": 40,
    "status": "DATA_UNAVAILABLE",
    "file_path": "",
    "size": 0,
    "year": null,
    "all_files": [],
    "file_count": 0,
    "timestamp": "2026-06-07T12:47:13.729845"
  },
  "Siaya": {
    "county_name": "Siaya",
    "county_code": 41,
    "status": "DATA_UNAVAILABLE",
    "file_path": "",
    "size": 0,
    "year": null,
    "all_files": [],
    "file_count": 0,
    "timestamp": "2026-06-07T12:47:13.730424"
  },
  "Kisumu": {
    "county_name": "Kisumu",
    "county_code": 42,
    "status": "AVAILABLE",
    "file_path": "D:/personal projects/Project data/Kisumu/2024-Statistical-Abstract-Kisumu-County.pdf",
    "size": 3417652,
    "year": 2024,
    "all_files": [
      "D:/personal projects/Project data/Kisumu/2024-Statistical-Abstract-Kisumu-County.pdf"
    ],
    "file_count": 1,
    "timestamp": "2026-06-07T03:02:08.647900"
  },
  "Homa Bay": {
    "county_name": "Homa Bay",
    "county_code": 43,
    "status": "AVAILABLE",
    "file_path": "D:/personal projects/Project data/Homa Bay/2024-Statistical-Abstract-Homa-Bay-County.pdf",
    "size": 13409505,
    "year": 2024,
    "all_files": [
      "D:/personal projects/Project data/Homa Bay/2024-Statistical-Abstract-Homa-Bay-County.pdf"
    ],
    "file_count": 1,
    "timestamp": "2026-06-07T03:02:16.423788"
  },
  "Migori": {
    "county_name": "Migori",
    "county_code": 44,
    "status": "DATA_UNAVAILABLE",
    "file_path": "",
    "size": 0,
    "year": null,
    "all_files": [],
    "file_count": 0,
    "timestamp": "2026-06-07T12:47:13.732668"
  },
  "Kisii": {
    "county_name": "Kisii",
    "county_code": 45,
    "status": "AVAILABLE",
    "file_path": "D:/personal projects/Project data/Kisii/2015-County-Statistical-Abstracts-Kisii.pdf",
    "size": 626230,
    "year": 2015,
    "all_files": [
      "D:/personal projects/Project data/Kisii/2015-County-Statistical-Abstracts-Kisii.pdf"
    ],
    "file_count": 1,
    "timestamp": "2026-06-07T03:02:20.382074"
  },
  "Nyamira": {
    "county_name": "Nyamira",
    "county_code": 46,
    "status": "DATA_UNAVAILABLE",
    "file_path": "",
    "size": 0,
    "year": null,
    "all_files": [],
    "file_count": 0,
    "timestamp": "2026-06-07T12:47:13.734346"
  },
  "Nairobi": {
    "county_name": "Nairobi",
    "county_code": 47,
    "status": "DATA_UNAVAILABLE",
    "file_path": "",
    "size": 0,
    "year": null,
    "all_files": [],
    "file_count": 0,
    "timestamp": "2026-06-07T12:47:13.735020"
  }
}